LICENSE.txt
MANIFEST.in
README.rst
setup.py
agency/__init__.py
agency/__init__.pyc
agency/admin.py
agency/models.py
agency/urls.py
agency/migrations/0001_initial.py
agency/migrations/0002_auto__add_affiliation.py
agency/migrations/__init__.py
djarcheology_agency.egg-info/PKG-INFO
djarcheology_agency.egg-info/SOURCES.txt
djarcheology_agency.egg-info/dependency_links.txt
djarcheology_agency.egg-info/top_level.txt