Metadata-Version: 1.0
Name: djarcheology-agency
Version: 0.1
Summary: A Django app to manage people and their organizational affiliations from the perspective of                 archeological research.
Home-page: http://www.mankatostatearcheology.org/
Author: Andrew Brown
Author-email: andrew@mankatostatearcheology.org
License: GNU General Public License v3
Platform: UNKNOWN
Classifier: Environment :: Web Environment
Classifier: Framework :: Django
Classifier: Intended Audience :: Developers
Classifier: License :: OSI Approved :: GNU General Public License v3 (GPLv3)
Classifier: Operating System :: OS Independent
Classifier: Programming Language :: Python
Classifier: Programming Language :: Python :: 2.6
Classifier: Programming Language :: Python :: 2.7
Classifier: Topic :: Internet :: WWW/HTTP
Classifier: Topic :: Internet :: WWW/HTTP :: Dynamic Content
